remedy
remedy.py
setup.py
remedy.egg-info/PKG-INFO
remedy.egg-info/SOURCES.txt
remedy.egg-info/dependency_links.txt
remedy.egg-info/requires.txt
remedy.egg-info/top_level.txt