Metadata-Version: 1.0
Name: remedy
Version: 0.0.6
Summary: Yet another markdown to reveal translator
Home-page: UNKNOWN
Author: Ingo Fruend
Author-email: Ingo.Fruend@twentybn.com
License: UNKNOWN
Platform: UNKNOWN
